{
    "oscpu": null,
    "product": null,
    "vendor": null,
    "description": "Internet Explorer 8.0\t(Windows 7)",
    "buildID": null,
    "appName": "Microsoft Internet Explorer",
    "appCodeName": "Mozilla",
    "productSub": null,
    "appVersion": "4.0 (compatible; MSIE 8.0; Windows NT 6.1; WOW64; Trident/4.0; SLCC2; .NET CLR 2.0.50727; .NET CLR 3.5.30729; .NET CLR 3.0.30729; Media Center PC 6.0; .NET4.0C; .NET4.0E; InfoPath.2)",
    "appMinorVersion": "0",
    "platform": "Win32",
    "browserTag": "ie80",
    "version": "8.0",
    "vendorSub": null,
    "javaUserAgent": "Mozilla/4.0 (Windows 7 6.1) Java/%s",
    "userAgent": "Mozilla/4.0 (compatible; MSIE 8.0; Windows NT 6.1; WOW64; Trident/4.0; SLCC2; .NET CLR 2.0.50727; .NET CLR 3.5.30729; .NET CLR 3.0.30729; Media Center PC 6.0; .NET4.0C; .NET4.0E; InfoPath.2)",
    "cc_on": {
        "_jscript_version": "5.8"
    },
    "shellVariables": {
        "ALLUSERSPROFILE": "C:\\ProgramData",
        "APPDATA": "C:\\Users\\{{username}}\\AppData\\Roaming",
        "CommonProgramFiles": "C:\\Program Files\\Common Files",
        "CommonProgramFiles(x86)": "C:\\Program Files (x86)\\Common Files",
        "CommonProgramw6432": "C.\\Program Files\\Common Files",
        "COMPUTERNAME": "{{computername}}",
        "ComSpec": "C:\\Windows\\system32\\cmd.exe",
        "FP_NO_HOST_CHECK": "NO",
        "HOMEDRIVE": "C:",
        "HOMEPATH": "\\Users\\{{username}}",
        "LOCALAPPDATA": "C:\\Users\\{{username}}\\AppData\\Local",
        "LOGONSERVER": "\\\\{{computername}}",
        "NUMBER_OF_PROCESSORS": "2",
        "OS": "WINDOWS_NT",
        "Path": "C:\\ProgramData\\Oracle\\Java\\javapath;C:\\Windows\\system32;C:\\Windows;C:\\Windows\\System32\\Wbem;C:\\Windows\\System32\\WindowsPowerShell\\v1.0\\;C:\\Program Files (x86)\\Skype\\Phone\\",
        "PATHEXT": ".COM;.EXE;.BAT;.CMD;.VBS;.VBE;.JS;.JSE;.WSF;.WSH;.MSC",
        "PROCESSOR_ARCHITECTURE": "AMD64",
        "PROCESSOR_IDENTIFIER": "Intel64 Family 6 Model 58 Stepping 9, GenuineIntel",
        "PROCESSOR_LEVEL": "6",
        "PROCESSOR_REVISION": "3a09",
        "ProgramData": "C:\\ProgramData",
        "ProgramFiles": "C:\\Program Files",
        "ProgramFiles(x86)": "C:\\Program Files (x86)",
        "ProgramW6432": "C:\\Program Files",
        "PROMPT": "$P$G",
        "PSModulePath": "C:\\Windows\\system32\\WindowsPowerShell\\v1.0\\Modules\\",
        "PUBLIC": "C:\\Users\\Public",
        "SESSIONNAME": "Console",
        "SystemDrive": "C:",
        "SystemRoot": "C:\\Windows",
        "TEMP": "C:\\Users\\{{username}}\\AppData\\Local\\Temp",
        "TMP": "C:\\Users\\{{username}}\\AppData\\Local\\Temp",
        "USERDOMAIN": "{{computername}}",
        "USERNAME": "{{username}}",
        "USERPROFILE": "C:\\Users\\{{username}}",
        "windir": "C:\\Windows"
    },
    "specialFolders": {
        "AllUsersDesktop": "%PUBLIC%\\Desktop",
        "AllUsersStartMenu": "%ALLUSERSPROFILE%\\Microsoft\\Windows\\Start Menu",
        "AllUsersPrograms": "%ALLUSERSPROFILE%\\Microsoft\\Windows\\Start Menu\\Programs",
        "AllUsersStartup": "%ALLUSERSPROFILE%\\Microsoft\\Windows\\Start Menu\\Programs\\Startup",
        "Desktop": "%USERPROFILE%\\Desktop",
        "Favorites": "%USERPROFILE%\\Favorites",
        "Fonts": "%windir%\\Fonts",
        "MyDocuments": "%USERPROFILE%\\Documents",
        "NetHood": "%APPDATA%\\Microsoft\\Windows\\Network Shortcuts",
        "PrintHood": "%APPDATA%\\Microsoft\\Windows\\Printer Shortcuts",
        "Programs": "%APPDATA%\\Microsoft\\Windows\\Start Menu\\Programs",
        "Recent": "%APPDATA%\\Microsoft\\Windows\\Recent",
        "SendTo": "%APPDATA%\\Microsoft\\Windows\\SendTo",
        "StartMenu": "%APPDATA%\\Microsoft\\Windows\\Start Menu",
        "Startup": "%APPDATA%\\Microsoft\\Windows\\Start Menu\\Programs\\Startup",
        "Templates": "%APPDATA%\\Microsoft\\Windows\\Templates"
    },
    "id": 130101
}
